rotagent/__init__.py
rotagent/agent.py
rotagent/client.py
rotagent/dev_tools.py
rotagent/keys.py
rotagent-0.1.0.dist-info/licenses/LICENSE
rotagent-0.1.0.dist-info/METADATA
rotagent-0.1.0.dist-info/WHEEL
rotagent-0.1.0.dist-info/top_level.txt
rotagent-0.1.0.dist-info/RECORD
