Metadata-Version: 2.4
Name: rotagent
Version: 0.1.0
Summary: Agent authentication and orchestrator client utilities for secure multi-agent communication
Author-email: Oleg Yaruchyk <yaruchyk.o@gmail.com>
License-Expression: MIT
Project-URL: Homepage, https://github.com/yaruchyo/rotagent
Project-URL: Repository, https://github.com/yaruchyo/rotagent
Project-URL: Documentation, https://github.com/yaruchyo/rotagent#readme
Project-URL: Issues, https://github.com/yaruchyo/rotagent/issues
Keywords: orchestrator,agent,authentication,jwt,security,multi-agent
Classifier: Development Status :: 3 - Alpha
Classifier: Intended Audience :: Developers
Classifier: Operating System :: OS Independent
Classifier: Programming Language :: Python :: 3
Classifier: Programming Language :: Python :: 3.9
Classifier: Programming Language :: Python :: 3.10
Classifier: Programming Language :: Python :: 3.11
Classifier: Programming Language :: Python :: 3.12
Classifier: Programming Language :: Python :: 3.13
Classifier: Topic :: Security
Classifier: Topic :: Software Development :: Libraries :: Python Modules
Requires-Python: >=3.9
License-File: LICENSE
Requires-Dist: flask>=2.0.0
Requires-Dist: PyJWT>=2.0.0
Requires-Dist: aiohttp>=3.8.0
Requires-Dist: cryptography>=3.4.0
Requires-Dist: python-dotenv>=0.19.0
Provides-Extra: dev
Requires-Dist: pytest>=7.0.0; extra == "dev"
Requires-Dist: pytest-asyncio>=0.20.0; extra == "dev"
Requires-Dist: black>=23.0.0; extra == "dev"
Requires-Dist: flake8>=6.0.0; extra == "dev"
Dynamic: license-file
